statsig_mcp/__init__.py
statsig_mcp/__main__.py
statsig_mcp/server.py
statsig_mcp/statsig_client.py
statsig_mcp/types.py
statsig_mcp-1.0.0.dist-info/METADATA
statsig_mcp-1.0.0.dist-info/WHEEL
statsig_mcp-1.0.0.dist-info/entry_points.txt
statsig_mcp-1.0.0.dist-info/licenses/LICENSE
statsig_mcp-1.0.0.dist-info/RECORD
