Metadata-Version: 2.4
Name: statsig-mcp
Version: 1.0.0
Summary: Model Context Protocol server for Statsig client SDK
Project-URL: Homepage, https://github.com/GeLi2001/statsig-mcp
Project-URL: Documentation, https://github.com/GeLi2001/statsig-mcp#readme
Project-URL: Repository, https://github.com/GeLi2001/statsig-mcp
Project-URL: Issues, https://github.com/GeLi2001/statsig-mcp/issues
Project-URL: Changelog, https://github.com/GeLi2001/statsig-mcp/releases
Author-email: Ge Li <geli2001@berkeley.edu>
License: MIT
License-File: LICENSE
Keywords: ai,feature-flags,llm,mcp,model-context-protocol,statsig
Classifier: Development Status :: 4 - Beta
Classifier: Intended Audience :: Developers
Classifier: License :: OSI Approved :: MIT License
Classifier: Programming Language :: Python :: 3
Classifier: Programming Language :: Python :: 3.10
Classifier: Programming Language :: Python :: 3.11
Classifier: Programming Language :: Python :: 3.12
Classifier: Topic :: Communications
Classifier: Topic :: Scientific/Engineering :: Artificial Intelligence
Classifier: Topic :: Software Development :: Libraries :: Python Modules
Requires-Python: >=3.10
Requires-Dist: mcp>=1.0.0
Requires-Dist: statsig-python-core>=0.5.0
Requires-Dist: typing-extensions>=4.0.0
Provides-Extra: dev
Requires-Dist: black>=23.0.0; extra == 'dev'
Requires-Dist: mypy>=1.0.0; extra == 'dev'
Requires-Dist: pytest-asyncio>=0.21.0; extra == 'dev'
Requires-Dist: pytest>=7.0.0; extra == 'dev'
Requires-Dist: ruff>=0.1.0; extra == 'dev'
Requires-Dist: twine>=4.0.0; extra == 'dev'
